chunkblocks/__init__.py
chunkblocks/global_offset_array.py
chunkblocks/iterators.py
chunkblocks/models.py
chunkblocks-0.5.1.dist-info/AUTHORS.rst
chunkblocks-0.5.1.dist-info/LICENSE
chunkblocks-0.5.1.dist-info/METADATA
chunkblocks-0.5.1.dist-info/WHEEL
chunkblocks-0.5.1.dist-info/top_level.txt
chunkblocks-0.5.1.dist-info/RECORD
